README.md
setup.py
cipwizard/__init__.py
cipwizard.egg-info/PKG-INFO
cipwizard.egg-info/SOURCES.txt
cipwizard.egg-info/dependency_links.txt
cipwizard.egg-info/entry_points.txt
cipwizard.egg-info/top_level.txt
cipwizard/analysis/__init__.py
cipwizard/analysis/analysis.py
cipwizard/analysis/cluster.py
cipwizard/analysis/coding.py
cipwizard/analysis/flows.py
cipwizard/analysis/hashtags.py
cipwizard/analysis/network.py
cipwizard/analysis/nlp.py
cipwizard/analysis/selection.py
cipwizard/analysis/temporal.py
cipwizard/analysis/topic.py
cipwizard/analysis/trees.py
cipwizard/analysis/users.py
cipwizard/core/__init__.py
cipwizard/core/json_util.py
cipwizard/core/sql_statements.py
cipwizard/core/troubleshoot.py
cipwizard/core/upload.py
cipwizard/core/url_unwind.py
cipwizard/core/util.py
cipwizard/query/__init__.py
cipwizard/query/commands.py
cipwizard/query/time.py
cipwizard/query/twitter.py
cipwizard/request/__init__.py
cipwizard/request/hydrate.py
cipwizard/request/images.py
cipwizard/request/lists.py
cipwizard/request/search.py
cipwizard/request/timelines.py
cipwizard/visualization/__init__.py
cipwizard/visualization/viz.py